lfnt/app.py
lfnt/cli.py
lfnt/digestion.py
lfnt/static/package.json
lfnt/static/terminal.js
lfnt/static/xterm.js
lfnt/static/yarn.lock
lfnt/templates/environment.html
lfnt/templates/head.html
lfnt/templates/home.html
lfnt/templates/package.html
lfnt/templates/profile.html
lfnt/templates/styles.css
lfnt/templates/tail.html
lfnt-0.1.11.dist-info/entry_points.txt
lfnt-0.1.11.dist-info/WHEEL
lfnt-0.1.11.dist-info/METADATA
lfnt-0.1.11.dist-info/RECORD
