Metadata-Version: 2.1
Name: lfnt
Version: 0.1.11
Summary: For eating development-environment elephants.
Home-page: https://gitlab.com/2fifty6/lfnt
Author: Dan Swartz
Author-email: 2fifty6@gmail.com
Requires-Python: >=3.9,<4.0
Classifier: Programming Language :: Python :: 3
Classifier: Programming Language :: Python :: 3.10
Classifier: Programming Language :: Python :: 3.9
Requires-Dist: Flask (>=2.0.3,<3.0.0)
Requires-Dist: GitPython (>=3.1.27,<4.0.0)
Requires-Dist: awscli (>=1.22.82,<2.0.0)
Requires-Dist: click (>=8.0.4,<9.0.0)
Requires-Dist: click-configfile (>=0.2.3,<0.3.0)
Requires-Dist: configparser (>=5.2.0,<6.0.0)
Requires-Dist: pulumi (>=3.27.0,<4.0.0)
Project-URL: Repository, https://gitlab.com/2fifty6/lfnt
